progressdb/__init__.py
progressdb/client.py
progressdb-0.1.5.dist-info/METADATA
progressdb-0.1.5.dist-info/WHEEL
progressdb-0.1.5.dist-info/top_level.txt
progressdb-0.1.5.dist-info/RECORD
