Metadata-Version: 2.4
Name: progressdb
Version: 0.1.5
Summary: ProgressDB backend Python SDK
Author: ProgressDB
License: MIT
Requires-Python: >=3.8
